README.md
setup.py
qhxc_api/__init__.py
qhxc_api/openapi.py
qhxc_api.egg-info/PKG-INFO
qhxc_api.egg-info/SOURCES.txt
qhxc_api.egg-info/dependency_links.txt
qhxc_api.egg-info/top_level.txt