Metadata-Version: 2.1
Name: qhxc-api
Version: 0.2.2
Summary: An exchange open api SDK
Requires-Python: >=3.6
